simplemonads/__init__.py
simplemonads-1.0.12.dist-info/LICENSE
simplemonads-1.0.12.dist-info/WHEEL
simplemonads-1.0.12.dist-info/METADATA
simplemonads-1.0.12.dist-info/RECORD
