Metadata-Version: 2.1
Name: simplemonads
Version: 1.0.12
Summary: Easy to use monads (containers), with pattern matching, that improve the quality of your python code. Use Just to end checking for None, Success to end unhandled exceptions, Future for async, and Reader for dependencies.
Home-page: https://github.com/sdaves/simplemonads
License: Unlicense
Author: Stephen Daves
Requires-Python: >=3.5,<4.0
Classifier: License :: Other/Proprietary License
Classifier: Programming Language :: Python :: 3
Classifier: Programming Language :: Python :: 3.5
Classifier: Programming Language :: Python :: 3.6
Classifier: Programming Language :: Python :: 3.7
Classifier: Programming Language :: Python :: 3.8
Classifier: Programming Language :: Python :: 3.9
Project-URL: Repository, https://github.com/sdaves/simplemonads
